cli_veripy/__init__.py
cli_veripy/argument.py
cli_veripy/cli_args.py
cli_veripy/handler.py
cli_veripy/type_validation.py
cli_veripy-1.2.12.dist-info/LICENSE
cli_veripy-1.2.12.dist-info/METADATA
cli_veripy-1.2.12.dist-info/WHEEL
cli_veripy-1.2.12.dist-info/top_level.txt
cli_veripy-1.2.12.dist-info/RECORD
